scholarmetrics/__init__.py
scholarmetrics/metrics.py
scholarmetrics/tests/__init__.py
scholarmetrics/tests/test_metrics.py
scholarmetrics-0.2.2.dist-info/AUTHORS.rst
scholarmetrics-0.2.2.dist-info/LICENSE
scholarmetrics-0.2.2.dist-info/METADATA
scholarmetrics-0.2.2.dist-info/WHEEL
scholarmetrics-0.2.2.dist-info/top_level.txt
scholarmetrics-0.2.2.dist-info/RECORD
