Metadata-Version: 2.1
Name: scholarmetrics
Version: 0.2.2
Summary: Compute scholarly metrics in Python with Pandas and NumPy Edit
Author-email: "Michael E. Rose" <Michael.Ernst.Rose@gmail.com>
Maintainer-email: "Michael E. Rose" <Michael.Ernst.Rose@gmail.com>
License: MIT
Project-URL: Homepage, https://github.com/Michael-E-Rose/scholarmetrics
Project-URL: Bug Tracker, https://github.com/Michael-E-Rose/scholarmetrics/issues
Project-URL: Documentation (stable), https://scholarmetrics.readthedocs.io/en/stable/
Project-URL: Documentation (latest), https://scholarmetrics.readthedocs.io/en/latest/
Keywords: metrics,researchers,scientists,academics
Classifier: Development Status :: 4 - Beta
Classifier: Intended Audience :: Science/Research
Classifier: License :: OSI Approved :: MIT License
Classifier: Natural Language :: English
Classifier: Operating System :: OS Independent
Classifier: Programming Language :: Python :: 3.5
Classifier: Programming Language :: Python :: 3.6
Classifier: Programming Language :: Python :: 3.7
Classifier: Programming Language :: Python :: 3.8
Classifier: Programming Language :: Python :: 3.9
Classifier: Programming Language :: Python :: 3.10
Classifier: Topic :: Software Development :: Libraries :: Python Modules
Classifier: Topic :: Scientific/Engineering :: Information Analysis
License-File: LICENSE
License-File: AUTHORS.rst
